README.rst
pbts
pybtsync.py
setup.py
pybtsync.egg-info/PKG-INFO
pybtsync.egg-info/SOURCES.txt
pybtsync.egg-info/dependency_links.txt
pybtsync.egg-info/requires.txt
pybtsync.egg-info/top_level.txt