Metadata-Version: 1.1
Name: pybtsync
Version: 0.0.3
Summary: A Python module for the BitTorrent Sync API.
Home-page: https://github.com/tiagomacarios/pybtsync
Author: Tiago Macarios
Author-email: tiagomacarios <at> the google email
License: MIT
Download-URL: https://github.com/tiagomacarios/pybtsync
Keywords: bittorrent sync api
Platform: UNKNOWN
Classifier: Development Status :: 3 - Alpha
Classifier: Environment :: Console
Classifier: Intended Audience :: Developers
Classifier: License :: OSI Approved :: MIT License
Classifier: Natural Language :: English
Classifier: Operating System :: OS Independent
Classifier: Programming Language :: Python
Classifier: Topic :: Internet
Classifier: Topic :: Software Development
Classifier: Topic :: Utilities
